
[
  {
    "pertanyaan": "Berapa hasil 2 + 3?",
    "opsi": {
      "A": "4",
      "B": "5",
      "C": "6",
      "D": "7"
    },
    "jawaban": "B",
    "gambar": null
  },
  {
    "pertanyaan": "Apa nama binatang ini?",
    "opsi": {
      "A": "Kucing",
      "B": "Anjing",
      "C": "Kelinci",
      "D": "Kuda"
    },
    "jawaban": "A",
    "gambar": "https://github.com/husniercnproficient-cpu/cerdasin/blob/main/images/kucing.JPG?raw=true"
  },
  {
    "pertanyaan": "Gambar ini menunjukkan bentuk bangun?",
    "opsi": {
      "A": "Lingkaran",
      "B": "Persegi",
      "C": "Segitiga",
      "D": "Trapesium"
    },
    "jawaban": "C",
    "gambar": "https://www.bing.com/images/search?view=detailV2&ccid=A0ZureMt&id=10F5C999D604094C92D7AF577B0AAEA84D1FB3B3&thid=OIP.A0ZureMt_gEiQMbcnTiB0QHaEs&mediaurl=https%3a%2f%2fcdn.kibrispdr.org%2fdata%2f32%2fcontoh-bangun-datar-segitiga-11.jpg&exph=381&expw=600&q=bentuk+bangun+segitiga&FORM=IRPRST&ck=8A9F570352939C10C9446E644C7A1B1B&selectedIndex=32&itb=0"
  }
]
